consumer_framework/__init__.py
consumer_framework/__main__.py
consumer_framework/app.py
consumer_framework/command_parser.py
consumer_framework/events.py
consumer_framework/exceptions.py
consumer_framework/routers.py
consumer_framework-0.0.36.dist-info/METADATA
consumer_framework-0.0.36.dist-info/WHEEL
consumer_framework-0.0.36.dist-info/entry_points.txt
consumer_framework-0.0.36.dist-info/top_level.txt
consumer_framework-0.0.36.dist-info/RECORD
